hat/syslog/generator.py
hat/syslog/server/ui/script/snabbdom/thunk.js
hat/syslog/server/ui/icons/user-trash.svg
hat/syslog/server/ui/script/snabbdom/htmldomapi.js.map
hat/syslog/server/ui/script/details.js
hat/syslog/server/ui/style/details.css
hat/syslog/server/ui/script/snabbdom/hooks.js.map
hat/syslog/server/ui/script/snabbdom/index.js
hat/syslog/server/ui/script/snabbdom/htmldomapi.js
hat/syslog/server/main.py
hat/syslog/server/ui/script/snabbdom/jsx.d.ts
hat/syslog/server/ui/script/@hat-open/juggler/README.md
hat/syslog/server/ui/script/snabbdom/helpers/attachto.js.map
hat/syslog/server/ui/script/@hat-open/util/dragger.d.ts
hat/syslog/server/ui/script/snabbdom/modules/style.js
hat/syslog/server/ui/icons/view-refresh.svg
hat/syslog/server/ui/script/snabbdom/thunk.js.map
hat/syslog/server/ui/style/table.css
hat/syslog/server/backend.py
hat/syslog/server/ui/script/snabbdom/modules/attributes.d.ts
hat/syslog/encoder.py
hat/syslog/server/ui/script/snabbdom/tovnode.js
hat/syslog/server/ui/script/snabbdom/modules/props.d.ts
hat/syslog/server/ui/script/snabbdom/vnode.js
hat/syslog/server/ui/script/@hat-open/util/iter.d.ts
hat/syslog/server/ui/script/snabbdom/hooks.js
hat/syslog/server/ui/script/header.js
hat/syslog/server/ui/script/snabbdom/index.js.map
hat/syslog/handler.py
hat/syslog/server/ui/icons/open-menu.svg
hat/syslog/server/ui/icons/go-top.svg
hat/syslog/server/ui/script/@hat-open/util/vnode.d.ts
hat/syslog/server/ui/script/@hat-open/renderer/vdom.js
hat/syslog/server/ui/favicon.ico
hat/syslog/server/ui/script/snabbdom/thunk.d.ts
hat/syslog/server/ui/script/snabbdom/tovnode.js.map
hat/syslog/server/ui/script/@hat-open/util/file.d.ts
hat/syslog/server/ui/script/@hat-open/util/promise.d.ts
hat/syslog/server/ui/script/snabbdom/hooks.d.ts
hat/syslog/server/ui/script/snabbdom/is.d.ts
hat/syslog/server/ui/script/@hat-open/util/package.json
hat/syslog/server/ui/script/snabbdom/modules/dataset.d.ts
hat/syslog/server/ui/script/@hat-open/util/misc.d.ts
hat_syslog-0.7.26.dist-info/LICENSE
hat_syslog-0.7.26.dist-info/entry_points.txt
hat_syslog-0.7.26.dist-info/METADATA
hat_syslog-0.7.26.dist-info/WHEEL
hat_syslog-0.7.26.dist-info/RECORD
