Metadata-Version: 2.1
Name: hat-syslog
Version: 0.7.26
Summary: Hat Syslog
License: Apache-2.0
Classifier: Programming Language :: Python :: 3
Classifier: License :: OSI Approved :: Apache Software License
Provides-Extra: dev
Requires-Dist: appdirs ~=1.4.4
Requires-Dist: hat-aio ~=0.7.12
Requires-Dist: hat-json ~=0.6.3
Requires-Dist: hat-juggler ~=0.7.1
Requires-Dist: hat-util ~=0.6.20
Requires-Dist: hat-doit ~=0.16.2; extra == 'dev'
Requires-Dist: sphinxcontrib-plantuml >=0.25; extra == 'dev'
Requires-Dist: sphinxcontrib-programoutput >=0.17; extra == 'dev'
Requires-Python: >=3.10
Project-URL: Homepage, http://hat-open.com
Project-URL: Repository, https://github.com/hat-open/hat-syslog.git
Project-URL: Documentation, http://hat-syslog.hat-open.com
